{   "DESCRIPTION":  "Set a custom points system for the results command ",
    "USAGE": "{{prefix}}setpoints",
    "EXAMPLES": "{{prefix}}setpoints",
    "embed1": "• View the current results system",
    "embed2": "• Set PMCO qualifiers system",
    "embed3": "• Set PMCO group stage system",
    "embed4": "• Set custom system",
    "toSave": "↪️*Set {{what}} as Results system for your server? `Yes/No`*",
    "Saved": "Results system has been set to {{this}}. Use `{{prefix}}points current` to preview.",
    "CurrentTitle": "CURRENT POINTS SYSTEM",
    "Save":"↪️*Do you want to save this as your results points system? `Yes / No`*",
    "Ques" : "↪️*Are you sure you want to change Results points system? `Yes/No`*",
    "AfterYes": "↪️Reply with the value of **Points** for **1st** rank:\n`↪️Reply End to end setup & discard changes:`",
    "RANK2": "↪️Reply with the value of **Points** for **2nd** rank:\n`↪️Reply End to end setup & discard changes:`",
    "RANK3": "↪️Reply with the value of **Points** for **3rd** rank:\n`↪️Reply End to end setup & discard changes:`",
    "RANK4": "↪️Reply with the value of **Points** for **4th** rank:\n`↪️Reply End to end setup & discard changes:`",
    "RANK5": "↪️Reply with the value of **Points** for **5th** rank:\n`↪️Reply End to end setup & discard changes:`",
    "RANK6": "↪️Reply with the value of **Points** for **6th** rank:\n`↪️Reply End to end setup & discard changes:`",
    "RANK7": "↪️Reply with the value of **Points** for **7th** rank:\n`↪️Reply End to end setup & discard changes:`",
    "RANK8": "↪️Reply with the value of **Points** for **8th** rank:\n`↪️Reply End to end setup & discard changes:`",
    "RANK9": "↪️Reply with the value of **Points** for **9th** rank:\n`↪️Reply End to end setup & discard changes:`",
    "RANK10": "↪️Reply with the value of **Points** for **10th** rank:\n`↪️Reply End to end setup & discard changes:`",
    "RANK11": "↪️Reply with the value of **Points** for **11th** rank:\n`↪️Reply End to end setup & discard changes:`",
    "RANK12": "↪️Reply with the value of **Points** for **12th** rank:\n`↪️Reply End to end setup & discard changes:`",
    "RANK13": "↪️Reply with the value of **Points** for **13th** rank:\n`↪️Reply End to end setup & discard changes:`",
    "RANK14": "↪️Reply with the value of **Points** for **14th** rank:\n`↪️Reply End to end setup & discard changes:`",
    "RANK15": "↪️Reply with the value of **Points** for **15th** rank:\n`↪️Reply End to end setup & discard changes:`",
    "RANK16": "↪️Reply with the value of **Points** for **16th** rank:\n`↪️Reply End to end setup & discard changes:`",
    "RANK17": "↪️Reply with the value of **Points** for **17th** rank:\n`↪️Reply End to end setup & discard changes:`",
    "RANK18": "↪️Reply with the value of **Points** for **18th** rank:\n`↪️Reply End to end setup & discard changes:`",
    "KILL":"↪️Reply with value of **Points** per **1** kill:\n`↪️Reply End to end setup & discard changes:`",
    "Var1":"Results system has been saved successfuly!",
    "Var2":"Changes on results system have been discard",
    "Var3":"Points setup has been discard"
}